Pype/__init__.py
Pype/plumber.py
Pype/pype.py
Pype/template/app.py
Pype/template/frontend/favicon.ico
Pype/template/frontend/index.html
Pype/template/frontend/pype.css
Pype/template/frontend/pype.js
Pype/template/frontend/styles.css
Pype/template/frontend/assets/logo.png
pype_framework-1.0.13.dist-info/LICENSE
pype_framework-1.0.13.dist-info/METADATA
pype_framework-1.0.13.dist-info/WHEEL
pype_framework-1.0.13.dist-info/entry_points.txt
pype_framework-1.0.13.dist-info/top_level.txt
pype_framework-1.0.13.dist-info/RECORD
