Metadata-Version: 2.1
Name: pype-framework
Version: 1.0.13
Summary: Python + HTML desktop app framework
Home-page: https://github.com/kokasmark/Pype
Author: Kokas Márk
Author-email: mark.kokas04@gmail.com
License: MIT
Classifier: Programming Language :: Python :: 3
Classifier: License :: OSI Approved :: MIT License
Classifier: Operating System :: OS Independent
Requires-Python: >=3.7
License-File: LICENSE
